qiscus_python_sdk/__init__.py
qiscus_python_sdk/api_client.py
qiscus_python_sdk-0.0.2.dist-info/LICENSE
qiscus_python_sdk-0.0.2.dist-info/METADATA
qiscus_python_sdk-0.0.2.dist-info/WHEEL
qiscus_python_sdk-0.0.2.dist-info/top_level.txt
qiscus_python_sdk-0.0.2.dist-info/RECORD
