Metadata-Version: 2.1
Name: qiscus-python-sdk
Version: 0.0.2
Summary: Qiscus SDK for Python (sync and async client)
Home-page: https://github.com/yomaaf/qiscus-python-sdk
Author: Rahmad Afandi
Author-email: rahmadafandiii@gmail.com
Classifier: Programming Language :: Python :: 3
Classifier: License :: OSI Approved :: MIT License
Classifier: Operating System :: OS Independent
Requires-Python: >=3.6
License-File: LICENSE
Requires-Dist: httpx
Requires-Dist: python-dotenv
